mlots/__init__.py
mlots/setup.py
mlots/utilities.py
mlots/models/__init__.py
mlots/models/_annoy.py
mlots/models/_hnsw.py
mlots/models/_knn.py
mlots/models/_nsw.py
mlots/transformation/__init__.py
mlots/transformation/_minirocket.py
mlots/transformation/_rocket.py
mlots/transformation/_rocket_algos/__init__.py
mlots/transformation/_rocket_algos/_minirocket.py
mlots/transformation/_rocket_algos/_minirocket_multivariate.py
mlots/transformation/_rocket_algos/_rocket.py
mlots-0.0.7.4.dist-info/LICENSE
mlots-0.0.7.4.dist-info/METADATA
mlots-0.0.7.4.dist-info/WHEEL
mlots-0.0.7.4.dist-info/top_level.txt
mlots-0.0.7.4.dist-info/RECORD
