Metadata-Version: 2.1
Name: mlots
Version: 0.0.7.4
Summary: Machine Learning Over Time-Series: A toolkit for time-series analysis
Home-page: http://mlots.readthedocs.io/
Author: Vivek Mahato
Author-email: vivek.mahato@ucdconnect.ie
License: UNKNOWN
Project-URL: Documentation, https://mlots.readthedocs.io/
Project-URL: Source, https://github.com/vivekmahato/mlots
Project-URL: Tracker, https://github.com/vivekmahato/mlots/issues
Platform: UNKNOWN
Classifier: Programming Language :: Python :: 3.7
Classifier: Programming Language :: Python :: 3.8
Classifier: License :: OSI Approved :: BSD License
Classifier: Operating System :: OS Independent
Requires-Dist: tslearn
Requires-Dist: numpy
Requires-Dist: scikit-learn
Requires-Dist: annoy
Requires-Dist: hnswlib
Requires-Dist: sortedcollections
Requires-Dist: tqdm
Requires-Dist: pandas
